MANIFEST.in
README
setup.cfg
setup.py
doc/Makefile
doc/cmip3.rst
doc/command.rst
doc/conf.py
doc/howto.rst
doc/index.rst
doc/intro.rst
doc/modules.rst
doc/product.rst
doc/schemes.rst
doc/esgf-sphinx-theme/layout-orig.html
doc/esgf-sphinx-theme/layout.html
doc/esgf-sphinx-theme/theme.conf
doc/esgf-sphinx-theme/static/basic.css
doc/esgf-sphinx-theme/static/esgf.css
doc/esgf-sphinx-theme/static/images/logo.png
doc/p_cmip5/configuration.rst
doc/p_cmip5/p_cmip5.rst
doc/p_cmip5/requested_subset_decision_tree_v0_5.pdf
drslib/__init__.py
drslib/cmip3.py
drslib/cmip5.py
drslib/config.py
drslib/cordex.py
drslib/drs.py
drslib/drs_command.py
drslib/drs_tree.py
drslib/drs_tree_check.py
drslib/exceptions.py
drslib/mapfile.py
drslib/mip_table.py
drslib/publisher_tree.py
drslib/specs.py
drslib/thredds.py
drslib/translate.py
drslib/translate_cmip3.py
drslib/translate_iface.py
drslib.egg-info/PKG-INFO
drslib.egg-info/SOURCES.txt
drslib.egg-info/dependency_links.txt
drslib.egg-info/entry_points.txt
drslib.egg-info/not-zip-safe
drslib.egg-info/requires.txt
drslib.egg-info/top_level.txt
drslib/data/CMIP5_models.csv
drslib/p_cmip5/__init__.py
drslib/p_cmip5/init.py
drslib/p_cmip5/product.py
drslib/p_cmip5/time_slices.py
drslib/p_cmip5/xls/CMIP5_archive_size_template.xls
drslib/p_cmip5/xls/expt_id_mapping.txt
drslib/p_cmip5/xls/standard_output_mod.xls
examples/__init__.py
examples/howto.txt
test/__init__.py
test/cmip3_test_ls
test/cmip5.output1.MOHC.HadGEM2-ES.rcp85.day.landIce.day.r1i1p1.ls
test/cmip5_nomodel_test_ls
test/cmip5_test.ls
test/cmor_test_ls
test/cordex_test_EUR-44.ls
test/drs_tree_shared.py
test/dummy_archive.zip
test/dups1.ls
test/dups2.ls
test/esmControl.ls
test/gen_drs.py
test/gridspec.ls
test/mohc_delivery.ls
test/multi_product.ls
test/multiversion_repair.ls
test/ncc_piControl.ls
test/ncc_rcp45.ls
test/ncc_sst2030.ls
test/opt_var.ls
test/realm_1.ls
test/sample_1.ini
test/sample_2.ini
test/sample_3.ini
test/sample_4.ini
test/sample_ipsl.ini
test/specs_1.ls
test/specs_2.ls
test/test_abspath.txt
test/test_cmip3.py
test/test_command.txt
test/test_command_p_cmip5.txt
test/test_cordex.py
test/test_dates.py
test/test_decadal.py
test/test_drs.py
test/test_drs_tree.py
