Metadata-Version: 1.1
Name: drslib
Version: 0.3.1p3
Summary: A library for processing the CMIP5 Data Reference Syntax
Home-page: http://esgf.org/esgf-drslib-site/
Author: Stephen Pascoe
Author-email: Stephen.Pascoe@stfc.ac.uk
License: BSD
Download-URL: http://ndg.nerc.ac.uk/dist
Platform: UNKNOWN
